MANIFEST.in
README.md
setup.py
exceptions/__init__.py
input/__init__.py
input/input_management.py
logmgmt/__init__.py
model/__init__.py
model/backend_information.py
model/login_path_information.py
model/page_information.py
model/process_type.py
model/locateloginpages/__init__.py
model/locateloginpages/additional_steps_to_show_login.py
model/locateloginpages/finding_strategy.py
model/privacydetection/__init__.py
model/ssodetection/__init__.py
model/ssodetection/search_algorithm.py
model/ssodetection/search_engine.py
model/ssodetection/sso_detection_strategy.py
model/ssosecurityanalyisis/__init__.py
model/ssosecurityanalyisis/distinct_backend_information.py
processes/__init__.py
processes/generic_process.py
processes/process_helper.py
processes/locateloginpages/__init__.py
processes/locateloginpages/locate_login_page_process.py
processes/privacydetection/__init__.py
processes/privacydetection/privacy_detection_process.py
processes/privacydetection/privacy_detection_provider.py
processes/ssolandscapeanalysis/__init__.py
processes/ssolandscapeanalysis/bing_search.py
processes/ssolandscapeanalysis/duck_duck_go_search.py
processes/ssolandscapeanalysis/local_sso_detection_process.py
processes/ssolandscapeanalysis/sso_detection_process.py
processes/ssolandscapeanalysis/sso_detection_service.py
processes/ssolandscapeanalysis/startpage_search.py
processes/ssolandscapeanalysis/locators/__init__.py
processes/ssolandscapeanalysis/locators/generic_text_locator.py
processes/ssolandscapeanalysis/locators/locator_helper.py
processes/ssolandscapeanalysis/locators/social_login_information.py
processes/ssolandscapeanalysis/locators/social_login_locator.py
processes/ssolandscapeanalysis/logorecognition/__init__.py
processes/ssolandscapeanalysis/logorecognition/configuration_logo_recognition.py
processes/ssolandscapeanalysis/logorecognition/logo_recognition.py
processes/ssolandscapeanalysis/logorecognition/logo_recognizer.py
sso_analysis_worker.egg-info/PKG-INFO
sso_analysis_worker.egg-info/SOURCES.txt
sso_analysis_worker.egg-info/dependency_links.txt
sso_analysis_worker.egg-info/requires.txt
sso_analysis_worker.egg-info/top_level.txt
