Metadata-Version: 2.1
Name: sso-analysis-worker
Version: 1.4.1
Summary: SSO Analysis Worker for brain
Home-page: https://sso-scanner-mgmt.it.hs-heilbronn.de/
Author: Maximilian Westers
Author-email: maximilian.westers@hs-heilbronn.de
